LICENSE.txt
evo_package_root/__init__.py
evo_package_root/automation/api.yaml
evo_package_root/automation/entity.yaml
evo_package_root/control/CRootApi.py
evo_package_root/control/__init__.py
evo_package_root/entity/EEApiConfigMap.py
evo_package_root/entity/EEApiPackage.py
evo_package_root/entity/EEApiPackageMap.py
evo_package_root/entity/__init__.py
evo_package_root/utility/URootApi.py
evo_package_root/utility/__init__.py
evo_package_root-2024.10.30111.dist-info/LICENSE.txt
evo_package_root-2024.10.30111.dist-info/METADATA
evo_package_root-2024.10.30111.dist-info/WHEEL
evo_package_root-2024.10.30111.dist-info/RECORD
